pandoc_plus/__init__.py
pandoc_plus/cleanup_md.py
pandoc_plus/support/beamer_default.yaml
pandoc_plus/support/class.docx
pandoc_plus/support/class.odt
pandoc_plus/support/fulton.png
pandoc_plus/support/letter.docx
pandoc_plus/support/package-lock.json
pandoc_plus/support/package.json
pandoc_plus/support/simple.docx
pandoc_plus/support/simple.odt
pandoc_plus/support/node_modules/.package-lock.json
pandoc_plus/support/node_modules/mathjax/LICENSE
pandoc_plus/support/node_modules/mathjax/README.md
pandoc_plus/support/node_modules/mathjax/package.json
pandoc_plus/support/node_modules/mathjax/es5/core.js
pandoc_plus/support/node_modules/mathjax/es5/latest.js
pandoc_plus/support/node_modules/mathjax/es5/loader.js
pandoc_plus/support/node_modules/mathjax/es5/mml-chtml.js
pandoc_plus/support/node_modules/mathjax/es5/mml-svg.js
pandoc_plus/support/node_modules/mathjax/es5/node-main.js
pandoc_plus/support/node_modules/mathjax/es5/startup.js
pandoc_plus/support/node_modules/mathjax/es5/tex-chtml-full-speech.js
pandoc_plus/support/node_modules/mathjax/es5/tex-chtml-full.js
pandoc_plus/support/node_modules/mathjax/es5/tex-chtml.js
pandoc_plus/support/node_modules/mathjax/es5/tex-mml-chtml.js
pandoc_plus/support/node_modules/mathjax/es5/tex-mml-svg.js
pandoc_plus/support/node_modules/mathjax/es5/tex-svg-full.js
pandoc_plus/support/node_modules/mathjax/es5/tex-svg.js
pandoc_plus/support/node_modules/mathjax/es5/a11y/assistive-mml.js
pandoc_plus/support/node_modules/mathjax/es5/a11y/complexity.js
pandoc_plus/support/node_modules/mathjax/es5/a11y/explorer.js
pandoc_plus/support/node_modules/mathjax/es5/a11y/semantic-enrich.js
pandoc_plus/support/node_modules/mathjax/es5/a11y/sre.js
pandoc_plus/support/node_modules/mathjax/es5/adaptors/liteDOM.js
pandoc_plus/support/node_modules/mathjax/es5/input/asciimath.js
pandoc_plus/support/node_modules/mathjax/es5/input/mml.js
pandoc_plus/support/node_modules/mathjax/es5/input/tex-base.js
pandoc_plus-0.0.6.dist-info/METADATA
pandoc_plus-0.0.6.dist-info/WHEEL
pandoc_plus-0.0.6.dist-info/top_level.txt
pandoc_plus-0.0.6.dist-info/RECORD
