Metadata-Version: 2.1
Name: pandoc_plus
Version: 0.0.6
Summary: Pandoc-plus is a collection of tools for making it easier to run pandoc
Home-page: https://github.com/danb0b/code_pandoc_plus
Author: Dan Aukes
Author-email: danaukes@danaukes.com
License: MIT
Classifier: Programming Language :: Python
Classifier: Programming Language :: Python :: 3
